anacondar/__init__.py
anacondar/terminal.py
anacondar-0.0.2.dist-info/METADATA
anacondar-0.0.2.dist-info/WHEEL
anacondar-0.0.2.dist-info/licenses/LICENSE
anacondar-0.0.2.dist-info/RECORD
