Metadata-Version: 2.1
Name: anacondar
Version: 0.0.2
Summary: A tool used to run shell/cmd commands via Python. Tries to print in a bash style format
Project-URL: GitHub, https://github.com/Buggem/anacondar
Project-URL: Bugs and Glitches, https://github.com/Buggem/anacondar/issues
Author: Buggem
License: MIT License
License-File: LICENSE
Classifier: License :: OSI Approved :: MIT License
Classifier: Operating System :: OS Independent
Classifier: Programming Language :: Python :: 3
Requires-Python: >=3.9
